phydrax/__init__.py
phydrax/_bvh.py
phydrax/_callable.py
phydrax/_doc.py
phydrax/_frozendict.py
phydrax/_strict.py
phydrax/constraints/__init__.py
phydrax/constraints/_base.py
phydrax/constraints/_bc_cfd.py
phydrax/constraints/_bc_em.py
phydrax/constraints/_bc_solid.py
phydrax/constraints/_bc_thermal.py
phydrax/constraints/_continuous_interior.py
phydrax/constraints/_discrete_interior.py
phydrax/constraints/_enforced.py
phydrax/constraints/_functional.py
phydrax/constraints/_functional_boundary.py
phydrax/constraints/_functional_initial.py
phydrax/constraints/_functional_integral.py
phydrax/constraints/_integral.py
phydrax/constraints/_interpolate.py
phydrax/constraints/_ode.py
phydrax/constraints/_pointset.py
phydrax/domain/__init__.py
phydrax/domain/_base.py
phydrax/domain/_components.py
phydrax/domain/_dataset.py
phydrax/domain/_domain.py
phydrax/domain/_function.py
phydrax/domain/_grid.py
phydrax/domain/_model_function.py
phydrax/domain/_product_domain.py
phydrax/domain/_sampling.py
phydrax/domain/_scalar.py
phydrax/domain/_structure.py
phydrax/domain/_time.py
phydrax/domain/geometry1d/__init__.py
phydrax/domain/geometry1d/_base.py
phydrax/domain/geometry1d/_primitives.py
phydrax/domain/geometry2d/__init__.py
phydrax/domain/geometry2d/_base.py
phydrax/domain/geometry2d/_from_cad.py
phydrax/domain/geometry2d/_primitives.py
phydrax/domain/geometry3d/__init__.py
phydrax/domain/geometry3d/_base.py
phydrax/domain/geometry3d/_cad_io.py
phydrax/domain/geometry3d/_constructors.py
phydrax/domain/geometry3d/_mesh.py
phydrax/domain/geometry3d/_normals.py
phydrax/domain/geometry3d/_primitives.py
phydrax/domain/geometry3d/_sampling.py
phydrax/domain/geometry3d/_sampling_jax.py
phydrax/domain/geometry3d/_sdf.py
phydrax/domain/geometry3d/_utils.py
phydrax/nn/__init__.py
phydrax/nn/_utils.py
phydrax/nn/activations/__init__.py
phydrax/nn/activations/_adaptive_activation.py
phydrax/nn/activations/_stan.py
phydrax/nn/models/__init__.py
phydrax/nn/models/_utils.py
phydrax-0.1.1.dist-info/METADATA
phydrax-0.1.1.dist-info/WHEEL
phydrax-0.1.1.dist-info/licenses/LICENSE
phydrax-0.1.1.dist-info/RECORD
