Metadata-Version: 2.4
Name: phydrax
Version: 0.1.1
Author-email: Phydra Labs <leonard@phydra.ai>
License-File: LICENSE
Requires-Python: <4.0,>=3.11
Requires-Dist: build123d>=0.10.0
Requires-Dist: coordax==0.2.3
Requires-Dist: equinox==0.13.2
Requires-Dist: evosax>=0.2.0
Requires-Dist: interpax>=0.3.12
Requires-Dist: jax>=0.8.2
Requires-Dist: jaxtyping>=0.3.5
Requires-Dist: manifold3d>=3.3.2
Requires-Dist: meshio>=5.3.5
Requires-Dist: opt-einsum>=3.4.0
Requires-Dist: optax>=0.2.6
Requires-Dist: orthax>=0.2.7
Requires-Dist: pyvista>=0.46.4
Requires-Dist: quadax>=0.2.11
Requires-Dist: trimesh[easy]>=4.11.1
Provides-Extra: docs
Requires-Dist: griffe==1.7.3; extra == 'docs'
Requires-Dist: hippogriffe==0.2.2; extra == 'docs'
Requires-Dist: mkdocs-include-exclude-files==0.1.0; extra == 'docs'
Requires-Dist: mkdocs-material==9.6.7; extra == 'docs'
Requires-Dist: mkdocs==1.6.1; extra == 'docs'
Requires-Dist: mkdocstrings-python==1.16.8; extra == 'docs'
Requires-Dist: mkdocstrings==0.28.3; extra == 'docs'
Requires-Dist: pymdown-extensions==10.14.3; extra == 'docs'
Provides-Extra: qa
Requires-Dist: ruff>=0.14.14; extra == 'qa'
Requires-Dist: ty>=0.0.13; extra == 'qa'
Provides-Extra: tests
Requires-Dist: pytest-clarity>=1.0.1; extra == 'tests'
Requires-Dist: pytest-rerunfailures>=16.1; extra == 'tests'
Requires-Dist: pytest-sugar>=1.1.1; extra == 'tests'
Requires-Dist: pytest-xdist>=3.8.0; extra == 'tests'
Requires-Dist: pytest>=9.0.2; extra == 'tests'
